{
"type": "FeatureCollection",
"name": "proposed_roads_widening_projects",
"crs": { "type": "name", "properties": { "name": "urn:ogc:def:crs:OGC:1.3:CRS84" } },
"features": [
{ "type": "Feature", "properties": { "type": "Road Widening", "name": "Expansion of Oke-Adu Junction - Fate - Iwo Raod Interchange" }, "geometry": { "type": "Point", "coordinates": [ 3.917766283220708, 7.394545102050587 ] } },
{ "type": "Feature", "properties": { "type": "Road Widening", "name": "Dualization of Gate - Old Ife road - Airport - Alakia Road" }, "geometry": { "type": "Point", "coordinates": [ 3.968490855650134, 7.391420526544604 ] } },
{ "type": "Feature", "properties": { "type": "Proposal for new Rondabout", "name": "Proposal for new Roundabout Gate - Ide Ape Junction" }, "geometry": { "type": "Point", "coordinates": [ 3.917377575841154, 7.397200246776583 ] } },
{ "type": "Feature", "properties": { "type": "Road Widening", "name": "Dualization of Idi Ape - Akobo - Odogbo Baracks Road" }, "geometry": { "type": "Point", "coordinates": [ 3.937363048362756, 7.424000945098774 ] } }
]
}
